chanjo2/__init__.py
chanjo2/auth.py
chanjo2/constants.py
chanjo2/crud/intervals.py
chanjo2/dbutil.py
chanjo2/demo/109_green.bed
chanjo2/demo/__init__.py
chanjo2/demo/intervals/exons_37.tsv
chanjo2/demo/intervals/exons_38.tsv
chanjo2/demo/intervals/genes_37.tsv
chanjo2/demo/intervals/genes_38.tsv
chanjo2/demo/intervals/transcripts_37.tsv
chanjo2/demo/intervals/transcripts_38.tsv
chanjo2/demo/panelapp_109_example.d4
chanjo2/endpoints/__init__.py
chanjo2/endpoints/coverage.py
chanjo2/endpoints/intervals.py
chanjo2/endpoints/overview.py
chanjo2/endpoints/report.py
chanjo2/logger.py
chanjo2/main.py
chanjo2/meta/__init__.py
chanjo2/meta/handle_bed.py
chanjo2/meta/handle_completeness_stats.py
chanjo2/meta/handle_coverage_stats.py
chanjo2/meta/handle_d4.py
chanjo2/meta/handle_load_intervals.py
chanjo2/meta/handle_report_contents.py
chanjo2/meta/utils.py
chanjo2/models/__init__.py
chanjo2/models/pydantic_models.py
chanjo2/models/sql_models.py
chanjo2/populate_demo.py
chanjo2/resources/XY_exons_GRCh37_noPAR.bed
chanjo2/resources/XY_exons_GRCh38_noPAR.bed
chanjo2/resources/XY_transcripts_GRCh37_noPAR.bed
chanjo2/resources/XY_transcripts_GRCh38_noPAR.bed
chanjo2/resources/__init__.py
chanjo2/resources/chrXY_exons_GRCh37_noPAR.bed
chanjo2/resources/chrXY_exons_GRCh38_noPAR.bed
chanjo2/resources/chrXY_transcripts_GRCh37_noPAR.bed
chanjo2/resources/chrXY_transcripts_GRCh38_noPAR.bed
chanjo2/static/main.css
chanjo2/templates/base-layout.html
chanjo2/templates/gene-overview.html
chanjo2/templates/mane-overview.html
chanjo2/templates/overview.html
chanjo2/templates/report.html
chanjo2-3.11.1.dist-info/METADATA
chanjo2-3.11.1.dist-info/WHEEL
chanjo2-3.11.1.dist-info/licenses/LICENSE
chanjo2-3.11.1.dist-info/RECORD
