Metadata-Version: 2.4
Name: chanjo2
Version: 3.11.1
Summary: Next generation coverage analysis
License-File: LICENSE
Author: northwestwitch
Author-email: chiara.rasi@scilifelab.se
Requires-Python: >=3.10,<4.0
Classifier: Programming Language :: Python :: 3
Classifier: Programming Language :: Python :: 3.10
Classifier: Programming Language :: Python :: 3.11
Classifier: Programming Language :: Python :: 3.12
Classifier: Programming Language :: Python :: 3.13
Classifier: Programming Language :: Python :: 3.14
Provides-Extra: m1
Requires-Dist: certifi (>=2024.7.4,<2025.0.0)
Requires-Dist: coloredlogs (>=15.0.1,<16.0.0)
Requires-Dist: cryptography (>=42.0.8,<44.0.0)
Requires-Dist: fastapi (>=0.121.0,<0.122.0)
Requires-Dist: gunicorn (==23.0.0)
Requires-Dist: httpx (>=0.28.1,<0.29.0)
Requires-Dist: importlib-resources (>=6.5.2,<7.0.0)
Requires-Dist: jinja2 (==3.1.6)
Requires-Dist: mkdocs (>=1.4.3,<2.0.0)
Requires-Dist: mysqlclient (>=2.1.0,<3.0.0)
Requires-Dist: pydantic (>=2.5.2,<3.0.0)
Requires-Dist: pytest (==7.4.4)
Requires-Dist: pytest-cov (>=4.0.0,<5.0.0)
Requires-Dist: pytest-mock (>=3.10.0,<4.0.0)
Requires-Dist: python-dotenv (>=1.0.0,<2.0.0)
Requires-Dist: python-jose[cryptography] (>=3.5.0,<4.0.0)
Requires-Dist: python-multipart (>=0.0.20,<0.0.21)
Requires-Dist: requests (>=2.28.2,<3.0.0)
Requires-Dist: respx (>=0.22.0,<0.23.0)
Requires-Dist: sqlalchemy (>=2.0.23,<3.0.0)
Requires-Dist: starlette (>=0.49.1)
Requires-Dist: tqdm (>=4.67.1,<5.0.0)
Requires-Dist: uvicorn (>=0.21.1,<0.22.0)
Requires-Dist: validators (>=0.34.0,<0.35.0)
